translate/__init__.py
translate/core/__init__.py
translate/core/asgi.py
translate/core/gunicorn.py
translate/core/settings.py
translate/core/urls.py
translate/core/utils/logger.py
translate/core/wsgi.py
translate/service/__init__.py
translate/service/admin.py
translate/service/apps.py
translate/service/filters.py
translate/service/import_spreadsheets/translations.csv
translate/service/management/__init__.py
translate/service/management/commands/__init__.py
translate/service/management/commands/bulk_export_to_csv.py
translate/service/management/commands/bulk_import_translations_from_csv.py
translate/service/management/commands/cleanup_custom_translation.py
translate/service/management/commands/delete_no_context_keys.py
translate/service/management/commands/export_csv.py
translate/service/management/commands/import_csv.py
translate/service/management/commands/import_translations.py
translate/service/management/commands/post_migrate_cmd_hooks.py
translate/service/migrations/0001_initial.py
translate/service/migrations/0002_alter_translation_key_alter_translation_language.py
translate/service/migrations/0003_translationkey_occ_views_gin.py
translate/service/migrations/0004_alter_language_lang_info_and_more.py
translate/service/migrations/__init__.py
translate/service/models.py
translate/service/paginations.py
translate/service/serializers.py
translate/service/static/assets/favicon.ico
translate/service/static/assets/img/swiss.jpeg
translate/service/static/assets/img/swiss_flg.jpeg
translate/service/static/css/style.css
translate/service/static/js/scripts.js
translate/service/templates/index.html
translate/service/tests/__init__.py
translate/service/tests/factories.py
translate/service/tests/fixtures/bulk_import_translations_from_csv_test_fixture.csv
translate/service/tests/fixtures/french_fixtures/locale/fr/LC_MESSAGES/django.po
translate/service/tests/fixtures/french_fixtures/snake_translations.json
melon_translate-0.17.1.dist-info/METADATA
melon_translate-0.17.1.dist-info/WHEEL
melon_translate-0.17.1.dist-info/RECORD
